policyengine_core/__init__.py
policyengine_core/model_api.py
policyengine_core/charts/__init__.py
policyengine_core/charts/api.py
policyengine_core/charts/bar.py
policyengine_core/charts/formatting.py
policyengine_core/commons/__init__.py
policyengine_core/commons/formulas.py
policyengine_core/commons/misc.py
policyengine_core/commons/rates.py
policyengine_core/country_template/__init__.py
policyengine_core/country_template/constants.py
policyengine_core/country_template/entities.py
policyengine_core/country_template/modelled_policies.yaml
policyengine_core/country_template/data/__init__.py
policyengine_core/country_template/data/datasets/__init__.py
policyengine_core/country_template/data/datasets/country_template_dataset.py
policyengine_core/country_template/parameters/benefits/basic_income.yaml
policyengine_core/country_template/parameters/benefits/housing_allowance.yaml
policyengine_core/country_template/parameters/benefits/index.yaml
policyengine_core/country_template/parameters/benefits/parenting_allowance/amount.yaml
policyengine_core/country_template/parameters/benefits/parenting_allowance/income_threshold.yaml
policyengine_core/country_template/parameters/general/age_of_majority.yaml
policyengine_core/country_template/parameters/general/age_of_retirement.yaml
policyengine_core/country_template/parameters/taxes/housing_tax.yaml
policyengine_core/country_template/parameters/taxes/income_tax_rate.yaml
policyengine_core/country_template/parameters/taxes/social_security_contribution.yaml
policyengine_core/country_template/reforms/__init__.py
policyengine_core/country_template/reforms/add_dynamic_variable.py
policyengine_core/country_template/reforms/add_new_tax.py
policyengine_core/country_template/reforms/flat_social_security_contribution.py
policyengine_core/country_template/reforms/modify_social_security_taxation.py
policyengine_core/country_template/reforms/removal_basic_income.py
policyengine_core/country_template/situation_examples/__init__.py
policyengine_core-3.23.6.dist-info/licenses/LICENSE
policyengine_core-3.23.6.dist-info/METADATA
policyengine_core-3.23.6.dist-info/WHEEL
policyengine_core-3.23.6.dist-info/entry_points.txt
policyengine_core-3.23.6.dist-info/top_level.txt
policyengine_core-3.23.6.dist-info/RECORD
