Metadata-Version: 2.4
Name: policyengine-core
Version: 3.23.6
Summary: Core microsimulation engine enabling country-specific policy models.
Home-page: https://github.com/policyengine/policyengine-core
Author: PolicyEngine
Author-email: hello@policyengine.org
License: https://www.fsf.org/licensing/licenses/agpl-3.0.html
Keywords: tax benefit microsimulation framework
Classifier: Development Status :: 5 - Production/Stable
Classifier: License :: OSI Approved :: GNU Affero General Public License v3
Classifier: Operating System :: POSIX
Classifier: Programming Language :: Python
Classifier: Programming Language :: Python :: 3.10
Classifier: Programming Language :: Python :: 3.11
Classifier: Programming Language :: Python :: 3.12
Classifier: Programming Language :: Python :: 3.13
Classifier: Topic :: Scientific/Engineering :: Information Analysis
Requires-Python: >=3.10
License-File: LICENSE
Requires-Dist: pytest<9,>=8
Requires-Dist: numpy<3,>=2.1.0
Requires-Dist: sortedcontainers<3
Requires-Dist: numexpr<3
Requires-Dist: dpath<3
Requires-Dist: psutil<7,>=6
Requires-Dist: wheel<1
Requires-Dist: h5py<4,>=3
Requires-Dist: requests<3,>=2
Requires-Dist: pandas>=1
Requires-Dist: plotly<6,>=5
Requires-Dist: ipython<9,>=8
Requires-Dist: pyvis>=0.3.2
Requires-Dist: microdf_python>=1.0.0
Requires-Dist: huggingface_hub>=0.25.1
Requires-Dist: standard-imghdr
Provides-Extra: dev
Requires-Dist: black; extra == "dev"
Requires-Dist: linecheck<1; extra == "dev"
Requires-Dist: jupyter-book<1; extra == "dev"
Requires-Dist: yaml-changelog<1; extra == "dev"
Requires-Dist: coverage; extra == "dev"
Requires-Dist: furo<2025; extra == "dev"
Requires-Dist: markupsafe<3; extra == "dev"
Requires-Dist: coverage; extra == "dev"
Requires-Dist: furo; extra == "dev"
Requires-Dist: mypy<2; extra == "dev"
Requires-Dist: sphinx==5.0.0; extra == "dev"
Requires-Dist: sphinx-argparse==0.4.0; extra == "dev"
Requires-Dist: sphinx-math-dollar==1.2.1; extra == "dev"
Requires-Dist: types-PyYAML==6.0.12.2; extra == "dev"
Requires-Dist: types-requests==2.28.11.7; extra == "dev"
Requires-Dist: types-setuptools==65.6.0.2; extra == "dev"
Requires-Dist: types-urllib3==1.26.25.4; extra == "dev"
Requires-Dist: pytest-rerunfailures<15,>=10; extra == "dev"
Dynamic: author
Dynamic: author-email
Dynamic: classifier
Dynamic: description
Dynamic: description-content-type
Dynamic: home-page
Dynamic: keywords
Dynamic: license
Dynamic: license-file
Dynamic: provides-extra
Dynamic: requires-dist
Dynamic: requires-python
Dynamic: summary
